yslee/__init__.py
yslee/sense/__init__.py
yslee/sense/client.py
yslee/sense/config.py
yslee/sense/event.py
yslee/sense/exceptions.py
yslee/sense/http_request.py
yslee/sense/requirements.txt
yslee/sense/result.py
yslee/sense/speaker.py
yslee/sense/version.py
yslee-1.0.9.dist-info/METADATA
yslee-1.0.9.dist-info/WHEEL
yslee-1.0.9.dist-info/RECORD
