Metadata-Version: 2.3
Name: yslee
Version: 1.0.9
Summary: Yslee Sense
Project-URL: Homepage, https://github.com/ysleeearai/yslee-sense-py
Project-URL: Issues, https://github.com/ysleeearai/yslee-sense-py/issues
Author-email: Yslee <support@yslee.ai>
Classifier: License :: OSI Approved :: MIT License
Classifier: Operating System :: OS Independent
Classifier: Programming Language :: Python :: 3
Requires-Python: >=3.9
Requires-Dist: soundfile
Requires-Dist: yslee-sense-api==1.7.90
